{
  "header": {
    "rows": [
      {
        "columns": [
          {
            "name": "Name",
            "sort": true,
            "reference": null,
            "contentModel": {
              "active": false,
              "value": ""
            },
            "styleClass": "name"
          },
          {
            "name": "Start Date",
            "reference": null,
            "contentModel": {
              "active": false,
              "value": ""
            },
            "styleClass": "date"
          },
          {
            "name": "Job Role",
            "reference": null,
            "contentModel": {
              "active": false,
              "value": ""
            },
            "styleClass": "role"
          },
          {
            "name": "Department",
            "reference": null,
            "contentModel": {
              "active": false,
              "value": ""
            },
            "styleClass": "department"
          },
          {
            "name": "Comment",
            "reference": null,
            "contentModel": {
              "active": false,
              "value": ""
            },
            "styleClass": "comment"
          }
        ],
        "styleClass": "header"
      }
    ]
  },
  "body": {
    "rows": [
      {
        "columns": [
          {
            "name": "Name",
            "reference": null,
            "contentModel": {
              "active": false,
              "value": "Ross"
            },
            "styleClass": "name"
          },
          {
            "name": "Start Date",
            "reference": null,
            "contentModel": {
              "active": false,
              "value": "01-12-2019"
            },
            "styleClass": "date"
          },
          {
            "name": "Job Role",
            "reference": null,
            "contentModel": {
              "active": false,
              "value": "developer"
            },
            "styleClass": "role"
          },
          {
            "name": "Department",
            "reference": null,
            "contentModel": {
              "active": false,
              "value": "developing an application"
            },
            "styleClass": "dept"
          },
          {
            "name": "Comment",
            "reference": null,
            "contentModel": {
              "active": false,
              "value": "row8"
            },
            "styleClass": "comment"
          }
        ],
        "styleClass": "row"
      },
      {
        "columns": [
          {
            "name": "Name",
            "reference": null,
            "contentModel": {
              "active": false,
              "value": "Andy"
            },
            "styleClass": "name"
          },
          {
            "name": "Start Date",
            "reference": null,
            "contentModel": {
              "active": false,
              "value": "02-12-2019"
            },
            "styleClass": "date"
          },
          {
            "name": "Job Role",
            "reference": null,
            "contentModel": {
              "active": false,
              "value": "developer"
            },
            "styleClass": "role"
          },
          {
            "name": "Department",
            "reference": null,
            "contentModel": {
              "active": false,
              "value": "developing an application"
            },
            "styleClass": "dept"
          },
          {
            "name": "Comment",
            "reference": null,
            "contentModel": {
              "active": false,
              "value": "row2"
            },
            "styleClass": "comment"
          }
        ],
        "styleClass": "row"
      },
     
      
      {
        "columns": [
          {
            "name": "Name",
            "reference": null,
            "contentModel": {
              "active": false,
              "value": "Casper"
            },
            "styleClass": "name"
          },
          {
            "name": "Start Date",
            "reference": null,
            "contentModel": {
              "active": false,
              "value": "03-12-2019"
            },
            "styleClass": "date"
          },
          {
            "name": "Job Role",
            "reference": null,
            "contentModel": {
              "active": false,
              "value": "developer"
            },
            "styleClass": "role"
          },
          {
            "name": "Department",
            "reference": null,
            "contentModel": {
              "active": false,
              "value": "developing an application"
            },
            "styleClass": "dept"
          },
          {
            "name": "Comment",
            "reference": null,
            "contentModel": {
              "active": false,
              "value": "row4"
            },
            "styleClass": "comment"
          }
        ],
        "styleClass": "row"
      },
      {
        "columns": [
          {
            "name": "Name",
            "reference": null,
            "contentModel": {
              "active": false,
              "value": "Bella"
            },
            "styleClass": "name"
          },
          {
            "name": "Start Date",
            "reference": null,
            "contentModel": {
              "active": false,
              "value": "04-12-2019"
            },
            "styleClass": "date"
          },
          {
            "name": "Job Role",
            "reference": null,
            "contentModel": {
              "active": false,
              "value": "developer"
            },
            "styleClass": "role"
          },
          {
            "name": "Department",
            "reference": null,
            "contentModel": {
              "active": false,
              "value": "developing an application"
            },
            "styleClass": "dept"
          },
          {
            "name": "Comment",
            "reference": null,
            "contentModel": {
              "active": false,
              "value": "row3"
            },
            "styleClass": "comment"
          }
        ],
        "styleClass": "row"
      },
      {
        "columns": [
          {
            "name": "Name",
            "reference": null,
            "contentModel": {
              "active": false,
              "value": "Alex"
            },
            "styleClass": "name"
          },
          {
            "name": "Start Date",
            "reference": null,
            "contentModel": {
              "active": false,
              "value": "05-12-2019"
            },
            "styleClass": "date"
          },
          {
            "name": "Job Role",
            "reference": null,
            "contentModel": {
              "active": false,
              "value": "developer"
            },
            "styleClass": "role"
          },
          {
            "name": "Department",
            "reference": null,
            "contentModel": {
              "active": false,
              "value": "developing an application"
            },
            "styleClass": "dept"
          },
          {
            "name": "Comment",
            "reference": null,
            "contentModel": {
              "active": false,
              "value": "row1"
            },
            "styleClass": "comment"
          }
        ],
        "styleClass": "row"
      },
      {
        "columns": [
          {
            "name": "Name",
            "reference": null,
            "contentModel": {
              "active": false,
              "value": "Monica"
            },
            "styleClass": "name"
          },
          {
            "name": "Start Date",
            "reference": null,
            "contentModel": {
              "active": false,
              "value": "12-12-2019"
            },
            "styleClass": "date"
          },
          {
            "name": "Job Role",
            "reference": null,
            "contentModel": {
              "active": false,
              "value": "developer"
            },
            "styleClass": "role"
          },
          {
            "name": "Department",
            "reference": null,
            "contentModel": {
              "active": false,
              "value": "developing an application"
            },
            "styleClass": "dept"
          },
          {
            "name": "Comment",
            "reference": null,
            "contentModel": {
              "active": false,
              "value": "row5"
            },
            "styleClass": "comment"
          }
        ],
        "styleClass": "row"
      },
      {
        "columns": [
          {
            "name": "Name",
            "reference": null,
            "contentModel": {
              "active": false,
              "value": "Phoebe"
            },
            "styleClass": "name"
          },
          {
            "name": "Start Date",
            "reference": null,
            "contentModel": {
              "active": false,
              "value": "12-12-2019"
            },
            "styleClass": "date"
          },
          {
            "name": "Job Role",
            "reference": null,
            "contentModel": {
              "active": false,
              "value": "developer"
            },
            "styleClass": "role"
          },
          {
            "name": "Department",
            "reference": null,
            "contentModel": {
              "active": false,
              "value": "developing an application"
            },
            "styleClass": "dept"
          },
          {
            "name": "Comment",
            "reference": null,
            "contentModel": {
              "active": false,
              "value": "row6"
            },
            "styleClass": "comment"
          }
        ],
        "styleClass": "row"
      },
      {
        "columns": [
          {
            "name": "Name",
            "reference": null,
            "contentModel": {
              "active": false,
              "value": "Rachel"
            },
            "styleClass": "name"
          },
          {
            "name": "Start Date",
            "reference": null,
            "contentModel": {
              "active": false,
              "value": "12-12-2019"
            },
            "styleClass": "date"
          },
          {
            "name": "Job Role",
            "reference": null,
            "contentModel": {
              "active": false,
              "value": "developer"
            },
            "styleClass": "role"
          },
          {
            "name": "Department",
            "reference": null,
            "contentModel": {
              "active": false,
              "value": "developing an application"
            },
            "styleClass": "dept"
          },
          {
            "name": "Comment",
            "reference": null,
            "contentModel": {
              "active": false,
              "value": "row7"
            },
            "styleClass": "comment"
          }
        ],
        "styleClass": "row"
      }
     
    ]
  }
}
